geometryMaths/__init__.py
geometryMaths-0.0.5.dist-info/LICENSE.txt
geometryMaths-0.0.5.dist-info/METADATA
geometryMaths-0.0.5.dist-info/WHEEL
geometryMaths-0.0.5.dist-info/top_level.txt
geometryMaths-0.0.5.dist-info/RECORD
