Metadata-Version: 2.1
Name: geometryMaths
Version: 0.0.5
Summary: A library made for making geometry in python simpler
Home-page: 
Author: The Goat
Author-email: 
License: MIT
Keywords: geometry
Classifier: Development Status :: 5 - Production/Stable
Classifier: Intended Audience :: Education
Classifier: Operating System :: OS Independent
Classifier: License :: OSI Approved :: MIT License
Classifier: Programming Language :: Python :: 3
License-File: LICENSE.txt
